{"_id":{"$oid":"60133a31de471e6d1e0d5f88"},"date":{"$date":"2021-01-28T00:00:00Z"},"currentSlot":0,"slots":[],"creator":{"$oid":"600f6351416a59301ed20588"},"createdAt":{"$date":"2021-01-28T22:26:57.235Z"},"updatedAt":{"$date":"2021-01-28T22:26:57.235Z"},"__v":0}
{"_id":{"$oid":"6023026365025310e3e35a57"},"date":{"$date":"2021-02-09T00:00:00Z"},"currentSlot":0,"slots":[],"creator":{"$oid":"600f6351416a59301ed20588"},"createdAt":{"$date":"2021-02-09T21:45:07.877Z"},"updatedAt":{"$date":"2021-02-09T21:45:07.877Z"},"__v":0}
{"_id":{"$oid":"602b1a6bb4246a29f9da8c47"},"date":{"$date":"2021-02-15T00:00:00Z"},"currentSlot":0,"slots":[{"_id":{"$oid":"602b1a80b4246a29f9da8c48"},"number":1,"time":"8:06:08 pm","patient":{"$oid":"600f85fd367a0634327f73e8"},"consultant":{"$oid":"600f8184416a59301ed20589"},"seen":false,"seenTime":""}],"creator":{"$oid":"600f8184416a59301ed20589"},"createdAt":{"$date":"2021-02-16T01:05:47.976Z"},"updatedAt":{"$date":"2021-02-16T01:06:08.27Z"},"__v":0}
